LICENSE
troposphere_awscommunity_applicationautoscaling_scheduledaction/__init__.py
troposphere_awscommunity_applicationautoscaling_scheduledaction/validators.py
troposphere_awscommunity_applicationautoscaling_scheduledaction-0.1.1.dist-info/LICENSE
troposphere_awscommunity_applicationautoscaling_scheduledaction-0.1.1.dist-info/METADATA
troposphere_awscommunity_applicationautoscaling_scheduledaction-0.1.1.dist-info/WHEEL
troposphere_awscommunity_applicationautoscaling_scheduledaction-0.1.1.dist-info/RECORD
