Metadata-Version: 2.1
Name: troposphere-awscommunity-applicationautoscaling-scheduledaction
Version: 0.1.1
Summary: Troposphere resource for AwsCommunity::ApplicationAutoscaling::ScheduledAction
License: LICENSE
Keywords: troposphere,aws-cloudformation
Author: John "Preston" Mille
Author-email: john@ews-network.net
Requires-Python: >=3.8,<4.0
Classifier: Development Status :: 3 - Alpha
Classifier: Intended Audience :: Developers
Classifier: Intended Audience :: Information Technology
Classifier: Intended Audience :: System Administrators
Classifier: License :: OSI Approved :: MIT License
Classifier: License :: Other/Proprietary License
Classifier: Natural Language :: English
Classifier: Programming Language :: Python :: 3
Classifier: Programming Language :: Python :: 3.8
Classifier: Programming Language :: Python :: 3.9
Classifier: Programming Language :: Python :: 3.10
Classifier: Programming Language :: Python :: 3.11
Classifier: Programming Language :: Python :: 3
Classifier: Programming Language :: Python :: 3.10
Classifier: Programming Language :: Python :: 3.8
Classifier: Programming Language :: Python :: 3.9
Requires-Dist: troposphere (>=4.3.2,<5.0.0)
Project-URL: Source, https://github.com/JohnPreston/troposphere-awscommunity-applicationautoscaling-scheduledaction.git
